reddio/__init__.py
reddio-0.0.2.dist-info/LICENSE
reddio-0.0.2.dist-info/WHEEL
reddio-0.0.2.dist-info/METADATA
reddio-0.0.2.dist-info/RECORD
