Metadata-Version: 2.1
Name: reddio
Version: 0.0.2
Summary: A simple GET only reddit API wrapper
License: MIT
Author: VarMonke
Author-email: var.monke@gmail.com
Requires-Python: >=3.8,<4.0
Classifier: License :: OSI Approved :: MIT License
Classifier: Programming Language :: Python :: 3
Classifier: Programming Language :: Python :: 3.8
Classifier: Programming Language :: Python :: 3.9
Classifier: Programming Language :: Python :: 3.10
Requires-Dist: aiohttp
